.travis.yml
AUTHORS
ChangeLog
LICENSE
README.rst
requirements.txt
setup.cfg
setup.py
Online_W3C_Validator.egg-info/PKG-INFO
Online_W3C_Validator.egg-info/SOURCES.txt
Online_W3C_Validator.egg-info/dependency_links.txt
Online_W3C_Validator.egg-info/entry_points.txt
Online_W3C_Validator.egg-info/not-zip-safe
Online_W3C_Validator.egg-info/pbr.json
Online_W3C_Validator.egg-info/requires.txt
Online_W3C_Validator.egg-info/top_level.txt
tests/test.html
tests/test0.html
tests/test_validator.py
w3c_validator/__init__.py
w3c_validator/validator.py