Metadata-Version: 2.1
Name: Online-W3C-Validator
Version: 0.3.21
Home-page: https://github.com/nad2000/W3C-Validator
Author: Radomirs Cirskis
Author-email: nad2000@gmail.com
License: MIT
Project-URL: Source Code, https://github.com/nad2000/W3C-Validator
Keywords: html validator,html,validator,checker,html5,w3
Classifier: Development Status :: 3 - Alpha
Classifier: Intended Audience :: Developers
Classifier: Intended Audience :: Science/Research
Classifier: Natural Language :: English
Classifier: License :: OSI Approved :: MIT License
Classifier: Operating System :: OS Independent
Classifier: Programming Language :: Python
Classifier: Programming Language :: Python :: 3.5
Classifier: Programming Language :: Python :: 3.6
Classifier: Programming Language :: Python :: 3.7
Classifier: Programming Language :: Python :: 3.8
Classifier: Programming Language :: Python :: 3.9
Classifier: Programming Language :: Python :: 3.10
Classifier: Programming Language :: Python :: 3.11
Provides-Extra: dev
Provides-Extra: test
License-File: LICENSE
License-File: AUTHORS
